ndx_spectrum/__init__.py
ndx_spectrum/test.py
ndx_spectrum/vis.py
ndx_spectrum/spec/ndx-spectrum.extensions.yaml
ndx_spectrum/spec/ndx-spectrum.namespace.yaml
ndx_spectrum-0.2.2.dist-info/LICENSE.txt
ndx_spectrum-0.2.2.dist-info/METADATA
ndx_spectrum-0.2.2.dist-info/WHEEL
ndx_spectrum-0.2.2.dist-info/top_level.txt
ndx_spectrum-0.2.2.dist-info/RECORD
